<OnlineCosmeticsShop>
    <Name>Ейвън</Name>
    <Employees>
        <Employee employeeId="employee1" gender="Мъж">
            <EmployeeName>Илиян</EmployeeName>
            <Address id="address1">
                <Country>България</Country>
                <City>София</City>
                <Street>бул.България</Street>
                <Number>34</Number>
            </Address>
            <Age>35</Age>
            <Position>Мениджър "Продажби"</Position>
            <Salary>3000</Salary>
            <Email>ilian@avon.bg</Email>
        </Employee>
        <Employee employeeId="employee2" gender="Жена">
            <EmployeeName>Станислава</EmployeeName>
            <Address addressId="address2">
                <Country>България</Country>
                <City>Враца</City>
                <Street>бул.Гео Милев</Street>
                <Number>84</Number>
            </Address>
            <Age>26</Age>
            <Position>Зонален мениджър</Position>
            <Email>stanislava@avon.bg</Email>
            <Telephone>0882532756</Telephone>
            <Salary>2500</Salary>
        </Employee>
    </Employees>
    <Orders orderId="order1" employeeId="employee1" limitPrice="500">
        <Order>
            <Products>
                <Product productId="product1" customerName="Пешо" count="2">
                    <Code>12345</Code>
                    <Category>Парфюми</Category>
                    <Description>Little Black Dress</Description>
                    <Price>21,99лв</Price>
                </Product>
            </Products>
            <TotalPrice>21,99лв</TotalPrice>
        </Order>
        <Order>
            <Products>
                <Product productId="product2" customerName="Николета" count="3">
                    <Code>12275</Code>
                    <Category>Кремове</Category>
                    <Description>Крем за лице Anew</Description>
                    <Price>15,99лв</Price>
                </Product>
            </Products>
            <TotalPrice>31,98лв</TotalPrice>
        </Order>
    </Orders>
    <Contacts>
        <Email>contacts@avon.bg</Email>
        <Phone>123 124 125</Phone>
        <Fax>555 444 333</Fax>
    </Contacts>
</OnlineCosmeticsShop>
